<?xml version="1.0" encoding="UTF-8"?>
<objects serializationModel="Studio.01.10.00">
    <object class="AudioFile" id="{6ea0be34-d354-476a-8426-e4058e16fe88}">
        <property name="assetPath">
            <value>bwork01.wav</value>
        </property>
        <property name="frequencyInKHz">
            <value>44.0999985</value>
        </property>
        <property name="channelCount">
            <value>2</value>
        </property>
        <property name="length">
            <value>1.9662131519274377</value>
        </property>
        <relationship name="masterAssetFolder">
            <destination>{2c0bfb92-5725-4939-bd50-0e9d83d048e8}</destination>
        </relationship>
    </object>
</objects>
